LICENSE.txt
MANIFEST.in
README.md
setup.cfg
setup.py
versioneer.py
src/Pepper.egg-info/PKG-INFO
src/Pepper.egg-info/SOURCES.txt
src/Pepper.egg-info/dependency_links.txt
src/Pepper.egg-info/entry_points.txt
src/Pepper.egg-info/not-zip-safe
src/Pepper.egg-info/requires.txt
src/Pepper.egg-info/top_level.txt
src/pepper/__init__.py
src/pepper/_version.py
src/pepper/abstract_symbol_tree.py
src/pepper/lexer.py
src/pepper/parser.py
src/pepper/parsetab.py
src/pepper/preprocessor.py
src/pepper/symbol_table.py