Metadata-Version: 1.1
Name: Pepper
Version: 0.0.3
Summary: Python-Enhanced PrePreocessor
Home-page: https://github.com/Devosoft/Pepper
Author: Jake Fenton
Author-email: jake@fenton.io
License: MIT License
Download-URL: https://github.com/devosoft/Pepper/archive/0.0.3.tar.gz
Keywords: preprocessor,C,C++,ply,compiler
Platform: UNKNOWN
Classifier: Development Status :: 2 - Pre-Alpha
Classifier: Intended Audience :: Developers
Classifier: License :: OSI Approved :: MIT License
Classifier: Operating System :: Unix
Classifier: Operating System :: POSIX
Classifier: Programming Language :: Python :: 3.6
Classifier: Topic :: Utilities
